peolymp/__init__.py
peolymp/abstract.py
peolymp/atlas.py
peolymp/client.py
peolymp/cognito.py
peolymp/community.py
peolymp/judge.py
peolymp/judge_contest.py
peolymp/ranker.py
peolymp/typewriter.py
peolymp/universe.py
peolymp/utils.py
peolymp-0.0.10.dist-info/METADATA
peolymp-0.0.10.dist-info/WHEEL
peolymp-0.0.10.dist-info/top_level.txt
peolymp-0.0.10.dist-info/RECORD
