Metadata-Version: 2.1
Name: peolymp
Version: 0.0.10
Home-page: https://github.com/ukroi
Author: Anton Tsypko
Author-email: tsypko@oi.in.ua
Requires-Dist: eolymp
Requires-Dist: requests
Requires-Dist: protobuf
